bongocat.py
bongocat-0.1.2.dist-info/LICENCE
bongocat-0.1.2.dist-info/METADATA
bongocat-0.1.2.dist-info/WHEEL
bongocat-0.1.2.dist-info/entry_points.txt
bongocat-0.1.2.dist-info/top_level.txt
bongocat-0.1.2.dist-info/RECORD
