Metadata-Version: 2.1
Name: bongocat
Version: 0.1.2
Summary: Bongo Cat overlay.
Home-page: https://github.com/Exahilosys/bongocat
Author: Exahilosys
License: MIT
Download-URL: https://github.com/Exahilosys/bongocat/archive/v0.1.2.tar.gz
Platform: UNKNOWN
Classifier: License :: OSI Approved :: MIT License
Classifier: Intended Audience :: Developers
Classifier: Natural Language :: English
Classifier: Operating System :: OS Independent
Classifier: Programming Language :: Python :: 3.7
Classifier: Topic :: Software Development :: Libraries
Classifier: Topic :: Software Development :: Libraries :: Python Modules
Classifier: Topic :: Utilities
Requires-Dist: docopt
Requires-Dist: keyboard
Requires-Dist: pillow
